pyngramroh/__init__.py
pyngramroh/__main__.py
pyngramroh/ngram.py
pyngramroh-0.0.1.dist-info/licenses/LICENSE
pyngramroh-0.0.1.dist-info/METADATA
pyngramroh-0.0.1.dist-info/WHEEL
pyngramroh-0.0.1.dist-info/top_level.txt
pyngramroh-0.0.1.dist-info/RECORD
